aioisotp/__init__.py
aioisotp/constants.py
aioisotp/exceptions.py
aioisotp/network.py
aioisotp/socketcan.py
aioisotp/sync.py
aioisotp/transport.py
aioisotp/version.py
aioisotp/transports/__init__.py
aioisotp/transports/isotpserver.py
aioisotp/transports/socketcan.py
aioisotp/transports/userspace.py
aioisotp-0.1.1.dist-info/METADATA
aioisotp-0.1.1.dist-info/RECORD
aioisotp-0.1.1.dist-info/WHEEL
aioisotp-0.1.1.dist-info/top_level.txt
