Metadata-Version: 2.1
Name: aioisotp
Version: 0.1.1
Summary: Asyncio implementation of ISO-TP (ISO 15765-2)
Home-page: https://github.com/christiansandberg/aioisotp
Author: Christian Sandberg
Author-email: christiansandberg@me.com
License: MIT
Keywords: CAN ISO-TP 15765
Platform: any
Classifier: Development Status :: 3 - Alpha
Classifier: Framework :: AsyncIO
Classifier: License :: OSI Approved :: MIT License
Classifier: Operating System :: OS Independent
Classifier: Programming Language :: Python :: 3
Classifier: Intended Audience :: Developers
Classifier: Topic :: Scientific/Engineering
Requires-Python: >=3.5
Requires-Dist: python-can (~=3.0)
